spellrst.py
spellrst-0.1.0.dist-info/entry_points.txt
spellrst-0.1.0.dist-info/LICENSE
spellrst-0.1.0.dist-info/WHEEL
spellrst-0.1.0.dist-info/METADATA
spellrst-0.1.0.dist-info/RECORD
