Metadata-Version: 2.1
Name: spellrst
Version: 0.1.0
Summary: Spell check reStructuredText.
Home-page: https://github.com/jwkvam/spellrst
License: UNKNOWN
Author: Jacques Kvam
Author-email: jwkvam+pypi@gmail.com
Requires-Python: >=3.6
Requires-Dist: click
Requires-Dist: docutils
Requires-Dist: spacy
